plotting/__init__.py
plotting/model.py
plotting/plots.py
plotting/py.typed
plotting/templates.py
plotting/titlerenderer.py
plotting/traces.py
plotting/data/ColdDraftF3APlane.obj
plotting/data/__init__.py
flightplotting-0.2.13.dist-info/METADATA
flightplotting-0.2.13.dist-info/WHEEL
flightplotting-0.2.13.dist-info/licenses/COPYING
flightplotting-0.2.13.dist-info/RECORD
