Metadata-Version: 2.4
Name: flightplotting
Version: 0.2.13
Summary: Add your description here
Author-email: Thomas David <thomasdavid0@gmail.com>
License-File: COPYING
Requires-Python: >=3.12
Requires-Dist: flightdata>=0.3.0
Requires-Dist: numpy>=2.1.3
Requires-Dist: pandas>=2.2.3
Requires-Dist: pfc-geometry
Requires-Dist: pfcschemas
Requires-Dist: plotly>=5.24.1
